abtem/__init__.py
abtem/_version.py
abtem/antialias.py
abtem/array.py
abtem/atoms.py
abtem/detectors.py
abtem/distributions.py
abtem/finite_difference.py
abtem/integrals.py
abtem/mcf.py
abtem/measurements.py
abtem/mtf.py
abtem/multislice.py
abtem/noise.py
abtem/reconstruct.py
abtem/scan.py
abtem/slicing.py
abtem/tilt.py
abtem/transfer.py
abtem/transform.py
abtem/waves.py
abtem/bloch/__init__.py
abtem/bloch/dynamical.py
abtem/bloch/indexing.py
abtem/bloch/matrix_exponential.py
abtem/bloch/utils.py
abtem/core/__init__.py
abtem/core/_cuda.py
abtem/core/abtem.yaml
abtem/core/axes.py
abtem/core/backend.py
abtem/core/chunks.py
abtem/core/colors.py
abtem/core/complex.py
abtem/core/config.py
abtem/core/constants.py
abtem/core/diagnostics.py
abtem/core/electron_configurations.py
abtem/core/energy.py
abtem/core/ensemble.py
abtem/core/fft.py
abtem/core/grid.py
abtem/core/units.py
abtem/core/utils.py
abtem/inelastic/__init__.py
abtem/inelastic/core_loss.py
abtem/inelastic/phonons.py
abtem/inelastic/plasmons.py
abtem/magnetism/__init__.py
abtem/magnetism/iam.py
abtem/magnetism/parametrizations/__init__.py
abtem/magnetism/parametrizations/data/lyon.json
abtem/parametrizations/__init__.py
abtem/parametrizations/data/kirkland.json
abtem/parametrizations/data/lobato.json
abtem/parametrizations/data/peng_high.json
abtem/parametrizations/data/peng_ionic.json
abtem/parametrizations/data/peng_low.json
abtem/parametrizations/data/waasmaier_kirfel.json
abtem/parametrizations/functions/__init__.py
abtem/parametrizations/functions/ewald.py
abtem/parametrizations/functions/kirkland.py
abtem/parametrizations/functions/lobato.py
abtem/parametrizations/functions/peng.py
abtem/potentials/__init__.py
abtem/potentials/_poisson.py
abtem/potentials/charge_density.py
abtem/potentials/gpaw.py
abtem/potentials/iam.py
abtem/prism/__init__.py
abtem/prism/_natural_neighbors.py
abtem/prism/_partitioned_s_matrix.py
abtem/prism/s_matrix.py
abtem/prism/utils.py
abtem/visualize/__init__.py
abtem-1.0.6.dist-info/LICENSE
abtem-1.0.6.dist-info/METADATA
abtem-1.0.6.dist-info/WHEEL
abtem-1.0.6.dist-info/top_level.txt
abtem-1.0.6.dist-info/RECORD
